pysaber/__init__.py
pysaber/pysaber.py
python_saber-0.1.1.dist-info/LICENSE
python_saber-0.1.1.dist-info/METADATA
python_saber-0.1.1.dist-info/WHEEL
python_saber-0.1.1.dist-info/top_level.txt
python_saber-0.1.1.dist-info/RECORD
