Metadata-Version: 2.1
Name: python-saber
Version: 0.1.1
Summary: A Beat Saber framework written in Python.
Home-page: https://github.com/CodeSoftGit/pysaber
Author: CodeSoft
Author-email: codesft@proton.me
Classifier: Programming Language :: Python :: 3
Classifier: License :: OSI Approved :: MIT License
Classifier: Operating System :: OS Independent
Requires-Python: >=3.9
License-File: LICENSE
Requires-Dist: pillow
